streampot/__init__.py
streampot/_client.py
streampot-0.3.2.dist-info/LICENSE
streampot-0.3.2.dist-info/METADATA
streampot-0.3.2.dist-info/WHEEL
streampot-0.3.2.dist-info/top_level.txt
streampot-0.3.2.dist-info/RECORD
