Metadata-Version: 2.1
Name: streampot
Version: 0.3.2
Summary: API client for StreamPot.io
Author: Jack Bridger, Ostap Brehin
License: Apache-2.0
Project-URL: Homepage, https://github.com/StreamPot/python-sdk
Project-URL: Changelog, https://github.com/StreamPot/python-sdk/releases
Project-URL: Issues, https://github.com/StreamPot/python-sdk/issues
Project-URL: CI, https://github.com/StreamPot/python-sdk/actions
Classifier: License :: OSI Approved :: Apache Software License
Requires-Python: >=3.8
License-File: LICENSE
Requires-Dist: requests >=2.25
Provides-Extra: test
Requires-Dist: pytest ; extra == 'test'
Requires-Dist: requests-mock ; extra == 'test'
